[{"principal":100000,"data":[{"kraken":"UNIUSD","return":0.0089},{"kraken":"LTCUSD","return":0.0089},{"kraken":"XRPUSD","return":0.0091},{"kraken":"XXBTZUSD","return":0.0103},{"kraken":"ETHUSD","return":0.0129},{"kraken":"ADAUSD","return":0.0142}]},{"principal":200000,"data":[{"kraken":"LTCUSD","return":0.0093},{"kraken":"XRPUSD","return":0.0094},{"kraken":"UNIUSD","return":0.0096},{"kraken":"XXBTZUSD","return":0.0111},{"kraken":"ETHUSD","return":0.0137},{"kraken":"ADAUSD","return":0.0145}]},{"principal":300000,"data":[{"kraken":"LTCUSD","return":0.0094},{"kraken":"XRPUSD","return":0.0095},{"kraken":"UNIUSD","return":0.0098},{"kraken":"XXBTZUSD","return":0.0114},{"kraken":"ETHUSD","return":0.014},{"kraken":"ADAUSD","return":0.0146}]},{"principal":400000,"data":[{"kraken":"LTCUSD","return":0.0094},{"kraken":"XRPUSD","return":0.0095},{"kraken":"UNIUSD","return":0.0099},{"kraken":"XXBTZUSD","return":0.0115},{"kraken":"ETHUSD","return":0.0141},{"kraken":"ADAUSD","return":0.0147}]},{"principal":500000,"data":[{"kraken":"LTCUSD","return":0.0094},{"kraken":"XRPUSD","return":0.0096},{"kraken":"UNIUSD","return":0.01},{"kraken":"XXBTZUSD","return":0.0116},{"kraken":"ETHUSD","return":0.0142},{"kraken":"ADAUSD","return":0.0147}]},{"principal":600000,"data":[{"kraken":"LTCUSD","return":0.0095},{"kraken":"XRPUSD","return":0.0096},{"kraken":"UNIUSD","return":0.0101},{"kraken":"XXBTZUSD","return":0.0116},{"kraken":"ETHUSD","return":0.0142},{"kraken":"ADAUSD","return":0.0147}]},{"principal":700000,"data":[{"kraken":"LTCUSD","return":0.0095},{"kraken":"XRPUSD","return":0.0096},{"kraken":"UNIUSD","return":0.0101},{"kraken":"XXBTZUSD","return":0.0117},{"kraken":"ETHUSD","return":0.0143},{"kraken":"ADAUSD","return":0.0147}]},{"principal":800000,"data":[{"kraken":"LTCUSD","return":0.0095},{"kraken":"XRPUSD","return":0.0096},{"kraken":"UNIUSD","return":0.0101},{"kraken":"XXBTZUSD","return":0.0117},{"kraken":"ETHUSD","return":0.0143},{"kraken":"ADAUSD","return":0.0147}]},{"principal":900000,"data":[{"kraken":"LTCUSD","return":0.0095},{"kraken":"XRPUSD","return":0.0096},{"kraken":"UNIUSD","return":0.0101},{"kraken":"XXBTZUSD","return":0.0117},{"kraken":"ETHUSD","return":0.0143},{"kraken":"ADAUSD","return":0.0147}]},{"principal":1000000,"data":[{"kraken":"LTCUSD","return":0.0095},{"kraken":"XRPUSD","return":0.0096},{"kraken":"UNIUSD","return":0.0102},{"kraken":"XXBTZUSD","return":0.0117},{"kraken":"ETHUSD","return":0.0143},{"kraken":"ADAUSD","return":0.0148}]}]
