[{"principal":100000,"data":[{"kraken":"ADAUSD","return":0.0048},{"kraken":"ETHUSD","return":0.0079},{"kraken":"XXBTZUSD","return":0.0085},{"kraken":"LTCUSD","return":0.0098},{"kraken":"XRPUSD","return":0.0102},{"kraken":"UNIUSD","return":0.0102}]},{"principal":200000,"data":[{"kraken":"ADAUSD","return":0.0051},{"kraken":"ETHUSD","return":0.0087},{"kraken":"XXBTZUSD","return":0.0094},{"kraken":"LTCUSD","return":0.0101},{"kraken":"XRPUSD","return":0.0105},{"kraken":"UNIUSD","return":0.0109}]},{"principal":300000,"data":[{"kraken":"ADAUSD","return":0.0052},{"kraken":"ETHUSD","return":0.0089},{"kraken":"XXBTZUSD","return":0.0097},{"kraken":"LTCUSD","return":0.0102},{"kraken":"XRPUSD","return":0.0106},{"kraken":"UNIUSD","return":0.0112}]},{"principal":400000,"data":[{"kraken":"ADAUSD","return":0.0052},{"kraken":"ETHUSD","return":0.009},{"kraken":"XXBTZUSD","return":0.0098},{"kraken":"LTCUSD","return":0.0102},{"kraken":"XRPUSD","return":0.0106},{"kraken":"UNIUSD","return":0.0113}]},{"principal":500000,"data":[{"kraken":"ADAUSD","return":0.0053},{"kraken":"ETHUSD","return":0.0091},{"kraken":"XXBTZUSD","return":0.0099},{"kraken":"LTCUSD","return":0.0102},{"kraken":"XRPUSD","return":0.0107},{"kraken":"UNIUSD","return":0.0113}]},{"principal":600000,"data":[{"kraken":"ADAUSD","return":0.0053},{"kraken":"ETHUSD","return":0.0092},{"kraken":"XXBTZUSD","return":0.0099},{"kraken":"LTCUSD","return":0.0103},{"kraken":"XRPUSD","return":0.0107},{"kraken":"UNIUSD","return":0.0114}]},{"principal":700000,"data":[{"kraken":"ADAUSD","return":0.0053},{"kraken":"ETHUSD","return":0.0092},{"kraken":"XXBTZUSD","return":0.01},{"kraken":"LTCUSD","return":0.0103},{"kraken":"XRPUSD","return":0.0107},{"kraken":"UNIUSD","return":0.0114}]},{"principal":800000,"data":[{"kraken":"ADAUSD","return":0.0053},{"kraken":"ETHUSD","return":0.0092},{"kraken":"XXBTZUSD","return":0.01},{"kraken":"LTCUSD","return":0.0103},{"kraken":"XRPUSD","return":0.0107},{"kraken":"UNIUSD","return":0.0115}]},{"principal":900000,"data":[{"kraken":"ADAUSD","return":0.0053},{"kraken":"ETHUSD","return":0.0093},{"kraken":"XXBTZUSD","return":0.01},{"kraken":"LTCUSD","return":0.0103},{"kraken":"XRPUSD","return":0.0107},{"kraken":"UNIUSD","return":0.0115}]},{"principal":1000000,"data":[{"kraken":"ADAUSD","return":0.0053},{"kraken":"ETHUSD","return":0.0093},{"kraken":"XXBTZUSD","return":0.01},{"kraken":"LTCUSD","return":0.0103},{"kraken":"XRPUSD","return":0.0107},{"kraken":"UNIUSD","return":0.0115}]}]
