[{"principal":100000,"data":[{"kraken":"UNIUSD","return":-0.0041},{"kraken":"XXBTZUSD","return":0.0146},{"kraken":"ETHUSD","return":0.0152},{"kraken":"ADAUSD","return":0.0156},{"kraken":"LTCUSD","return":0.0157},{"kraken":"XRPUSD","return":0.0166}]},{"principal":200000,"data":[{"kraken":"UNIUSD","return":-0.0034},{"kraken":"XXBTZUSD","return":0.0154},{"kraken":"ADAUSD","return":0.0159},{"kraken":"ETHUSD","return":0.016},{"kraken":"LTCUSD","return":0.016},{"kraken":"XRPUSD","return":0.0169}]},{"principal":300000,"data":[{"kraken":"UNIUSD","return":-0.0032},{"kraken":"XXBTZUSD","return":0.0157},{"kraken":"ADAUSD","return":0.016},{"kraken":"LTCUSD","return":0.0161},{"kraken":"ETHUSD","return":0.0163},{"kraken":"XRPUSD","return":0.017}]},{"principal":400000,"data":[{"kraken":"UNIUSD","return":-0.0031},{"kraken":"XXBTZUSD","return":0.0159},{"kraken":"ADAUSD","return":0.0161},{"kraken":"LTCUSD","return":0.0162},{"kraken":"ETHUSD","return":0.0164},{"kraken":"XRPUSD","return":0.0171}]},{"principal":500000,"data":[{"kraken":"UNIUSD","return":-0.003},{"kraken":"XXBTZUSD","return":0.0159},{"kraken":"ADAUSD","return":0.0161},{"kraken":"LTCUSD","return":0.0162},{"kraken":"ETHUSD","return":0.0165},{"kraken":"XRPUSD","return":0.0171}]},{"principal":600000,"data":[{"kraken":"UNIUSD","return":-0.003},{"kraken":"XXBTZUSD","return":0.016},{"kraken":"ADAUSD","return":0.0162},{"kraken":"LTCUSD","return":0.0162},{"kraken":"ETHUSD","return":0.0165},{"kraken":"XRPUSD","return":0.0171}]},{"principal":700000,"data":[{"kraken":"UNIUSD","return":-0.003},{"kraken":"XXBTZUSD","return":0.016},{"kraken":"ADAUSD","return":0.0162},{"kraken":"LTCUSD","return":0.0162},{"kraken":"ETHUSD","return":0.0165},{"kraken":"XRPUSD","return":0.0171}]},{"principal":800000,"data":[{"kraken":"UNIUSD","return":-0.0029},{"kraken":"XXBTZUSD","return":0.0161},{"kraken":"ADAUSD","return":0.0162},{"kraken":"LTCUSD","return":0.0163},{"kraken":"ETHUSD","return":0.0166},{"kraken":"XRPUSD","return":0.0171}]},{"principal":900000,"data":[{"kraken":"UNIUSD","return":-0.0029},{"kraken":"XXBTZUSD","return":0.0161},{"kraken":"ADAUSD","return":0.0162},{"kraken":"LTCUSD","return":0.0163},{"kraken":"ETHUSD","return":0.0166},{"kraken":"XRPUSD","return":0.0171}]},{"principal":1000000,"data":[{"kraken":"UNIUSD","return":-0.0029},{"kraken":"XXBTZUSD","return":0.0161},{"kraken":"ADAUSD","return":0.0162},{"kraken":"LTCUSD","return":0.0163},{"kraken":"ETHUSD","return":0.0166},{"kraken":"XRPUSD","return":0.0172}]}]
