[{"principal":100000,"data":[{"kraken":"ETHUSD","return":0.0045},{"kraken":"XRPUSD","return":0.0052},{"kraken":"XXBTZUSD","return":0.0054},{"kraken":"LTCUSD","return":0.0069},{"kraken":"ADAUSD","return":0.0106},{"kraken":"UNIUSD","return":0.0231}]},{"principal":200000,"data":[{"kraken":"ETHUSD","return":0.0054},{"kraken":"XRPUSD","return":0.0055},{"kraken":"XXBTZUSD","return":0.0062},{"kraken":"LTCUSD","return":0.0072},{"kraken":"ADAUSD","return":0.011},{"kraken":"UNIUSD","return":0.0239}]},{"principal":300000,"data":[{"kraken":"XRPUSD","return":0.0056},{"kraken":"ETHUSD","return":0.0057},{"kraken":"XXBTZUSD","return":0.0065},{"kraken":"LTCUSD","return":0.0073},{"kraken":"ADAUSD","return":0.0111},{"kraken":"UNIUSD","return":0.0241}]},{"principal":400000,"data":[{"kraken":"XRPUSD","return":0.0057},{"kraken":"ETHUSD","return":0.0058},{"kraken":"XXBTZUSD","return":0.0066},{"kraken":"LTCUSD","return":0.0073},{"kraken":"ADAUSD","return":0.0111},{"kraken":"UNIUSD","return":0.0242}]},{"principal":500000,"data":[{"kraken":"XRPUSD","return":0.0057},{"kraken":"ETHUSD","return":0.0059},{"kraken":"XXBTZUSD","return":0.0067},{"kraken":"LTCUSD","return":0.0074},{"kraken":"ADAUSD","return":0.0112},{"kraken":"UNIUSD","return":0.0243}]},{"principal":600000,"data":[{"kraken":"XRPUSD","return":0.0057},{"kraken":"ETHUSD","return":0.0059},{"kraken":"XXBTZUSD","return":0.0068},{"kraken":"LTCUSD","return":0.0074},{"kraken":"ADAUSD","return":0.0112},{"kraken":"UNIUSD","return":0.0244}]},{"principal":700000,"data":[{"kraken":"XRPUSD","return":0.0057},{"kraken":"ETHUSD","return":0.006},{"kraken":"XXBTZUSD","return":0.0068},{"kraken":"LTCUSD","return":0.0074},{"kraken":"ADAUSD","return":0.0112},{"kraken":"UNIUSD","return":0.0244}]},{"principal":800000,"data":[{"kraken":"XRPUSD","return":0.0057},{"kraken":"ETHUSD","return":0.006},{"kraken":"XXBTZUSD","return":0.0068},{"kraken":"LTCUSD","return":0.0074},{"kraken":"ADAUSD","return":0.0112},{"kraken":"UNIUSD","return":0.0244}]},{"principal":900000,"data":[{"kraken":"XRPUSD","return":0.0058},{"kraken":"ETHUSD","return":0.006},{"kraken":"XXBTZUSD","return":0.0069},{"kraken":"LTCUSD","return":0.0074},{"kraken":"ADAUSD","return":0.0112},{"kraken":"UNIUSD","return":0.0245}]},{"principal":1000000,"data":[{"kraken":"XRPUSD","return":0.0058},{"kraken":"ETHUSD","return":0.0061},{"kraken":"XXBTZUSD","return":0.0069},{"kraken":"LTCUSD","return":0.0074},{"kraken":"ADAUSD","return":0.0112},{"kraken":"UNIUSD","return":0.0245}]}]
