[{"principal":100000,"data":[{"kraken":"UNIUSD","return":0.0008},{"kraken":"LTCUSD","return":0.011},{"kraken":"ETHUSD","return":0.0114},{"kraken":"XXBTZUSD","return":0.0139},{"kraken":"XRPUSD","return":0.0146},{"kraken":"ADAUSD","return":0.0204}]},{"principal":200000,"data":[{"kraken":"UNIUSD","return":0.0014},{"kraken":"LTCUSD","return":0.0113},{"kraken":"ETHUSD","return":0.0122},{"kraken":"XRPUSD","return":0.0149},{"kraken":"XXBTZUSD","return":0.0149},{"kraken":"ADAUSD","return":0.0207}]},{"principal":300000,"data":[{"kraken":"UNIUSD","return":0.0016},{"kraken":"LTCUSD","return":0.0114},{"kraken":"ETHUSD","return":0.0125},{"kraken":"XRPUSD","return":0.015},{"kraken":"XXBTZUSD","return":0.0152},{"kraken":"ADAUSD","return":0.0208}]},{"principal":400000,"data":[{"kraken":"UNIUSD","return":0.0017},{"kraken":"LTCUSD","return":0.0114},{"kraken":"ETHUSD","return":0.0126},{"kraken":"XRPUSD","return":0.015},{"kraken":"XXBTZUSD","return":0.0153},{"kraken":"ADAUSD","return":0.0208}]},{"principal":500000,"data":[{"kraken":"UNIUSD","return":0.0018},{"kraken":"LTCUSD","return":0.0115},{"kraken":"ETHUSD","return":0.0127},{"kraken":"XRPUSD","return":0.015},{"kraken":"XXBTZUSD","return":0.0154},{"kraken":"ADAUSD","return":0.0209}]},{"principal":600000,"data":[{"kraken":"UNIUSD","return":0.0019},{"kraken":"LTCUSD","return":0.0115},{"kraken":"ETHUSD","return":0.0127},{"kraken":"XRPUSD","return":0.0151},{"kraken":"XXBTZUSD","return":0.0155},{"kraken":"ADAUSD","return":0.0209}]},{"principal":700000,"data":[{"kraken":"UNIUSD","return":0.0019},{"kraken":"LTCUSD","return":0.0115},{"kraken":"ETHUSD","return":0.0128},{"kraken":"XRPUSD","return":0.0151},{"kraken":"XXBTZUSD","return":0.0155},{"kraken":"ADAUSD","return":0.0209}]},{"principal":800000,"data":[{"kraken":"UNIUSD","return":0.0019},{"kraken":"LTCUSD","return":0.0115},{"kraken":"ETHUSD","return":0.0128},{"kraken":"XRPUSD","return":0.0151},{"kraken":"XXBTZUSD","return":0.0156},{"kraken":"ADAUSD","return":0.0209}]},{"principal":900000,"data":[{"kraken":"UNIUSD","return":0.0019},{"kraken":"LTCUSD","return":0.0115},{"kraken":"ETHUSD","return":0.0128},{"kraken":"XRPUSD","return":0.0151},{"kraken":"XXBTZUSD","return":0.0156},{"kraken":"ADAUSD","return":0.0209}]},{"principal":1000000,"data":[{"kraken":"UNIUSD","return":0.0019},{"kraken":"LTCUSD","return":0.0115},{"kraken":"ETHUSD","return":0.0128},{"kraken":"XRPUSD","return":0.0151},{"kraken":"XXBTZUSD","return":0.0156},{"kraken":"ADAUSD","return":0.0209}]}]
