[{"principal":100000,"data":[{"kraken":"ADAUSD","return":0.0077},{"kraken":"ETHUSD","return":0.0156},{"kraken":"XXBTZUSD","return":0.0181},{"kraken":"XRPUSD","return":0.0192},{"kraken":"LTCUSD","return":0.0203},{"kraken":"UNIUSD","return":0.0264}]},{"principal":200000,"data":[{"kraken":"ADAUSD","return":0.008},{"kraken":"ETHUSD","return":0.0163},{"kraken":"XXBTZUSD","return":0.0189},{"kraken":"XRPUSD","return":0.0195},{"kraken":"LTCUSD","return":0.0206},{"kraken":"UNIUSD","return":0.027}]},{"principal":300000,"data":[{"kraken":"ADAUSD","return":0.0081},{"kraken":"ETHUSD","return":0.0166},{"kraken":"XXBTZUSD","return":0.0192},{"kraken":"XRPUSD","return":0.0196},{"kraken":"LTCUSD","return":0.0207},{"kraken":"UNIUSD","return":0.0273}]},{"principal":400000,"data":[{"kraken":"ADAUSD","return":0.0082},{"kraken":"ETHUSD","return":0.0167},{"kraken":"XXBTZUSD","return":0.0193},{"kraken":"XRPUSD","return":0.0196},{"kraken":"LTCUSD","return":0.0208},{"kraken":"UNIUSD","return":0.0274}]},{"principal":500000,"data":[{"kraken":"ADAUSD","return":0.0082},{"kraken":"ETHUSD","return":0.0168},{"kraken":"XXBTZUSD","return":0.0194},{"kraken":"XRPUSD","return":0.0197},{"kraken":"LTCUSD","return":0.0208},{"kraken":"UNIUSD","return":0.0275}]},{"principal":600000,"data":[{"kraken":"ADAUSD","return":0.0082},{"kraken":"ETHUSD","return":0.0168},{"kraken":"XXBTZUSD","return":0.0195},{"kraken":"XRPUSD","return":0.0197},{"kraken":"LTCUSD","return":0.0208},{"kraken":"UNIUSD","return":0.0275}]},{"principal":700000,"data":[{"kraken":"ADAUSD","return":0.0083},{"kraken":"ETHUSD","return":0.0169},{"kraken":"XXBTZUSD","return":0.0195},{"kraken":"XRPUSD","return":0.0197},{"kraken":"LTCUSD","return":0.0208},{"kraken":"UNIUSD","return":0.0275}]},{"principal":800000,"data":[{"kraken":"ADAUSD","return":0.0083},{"kraken":"ETHUSD","return":0.0169},{"kraken":"XXBTZUSD","return":0.0195},{"kraken":"XRPUSD","return":0.0197},{"kraken":"LTCUSD","return":0.0208},{"kraken":"UNIUSD","return":0.0276}]},{"principal":900000,"data":[{"kraken":"ADAUSD","return":0.0083},{"kraken":"ETHUSD","return":0.0169},{"kraken":"XXBTZUSD","return":0.0196},{"kraken":"XRPUSD","return":0.0197},{"kraken":"LTCUSD","return":0.0208},{"kraken":"UNIUSD","return":0.0276}]},{"principal":1000000,"data":[{"kraken":"ADAUSD","return":0.0083},{"kraken":"ETHUSD","return":0.0169},{"kraken":"XXBTZUSD","return":0.0196},{"kraken":"XRPUSD","return":0.0197},{"kraken":"LTCUSD","return":0.0208},{"kraken":"UNIUSD","return":0.0276}]}]
