[{"principal":100000,"data":[{"kraken":"UNIUSD","return":0.0033},{"kraken":"ADAUSD","return":0.0082},{"kraken":"LTCUSD","return":0.0136},{"kraken":"XXBTZUSD","return":0.0176},{"kraken":"ETHUSD","return":0.0183},{"kraken":"XRPUSD","return":0.0186}]},{"principal":200000,"data":[{"kraken":"UNIUSD","return":0.0048},{"kraken":"ADAUSD","return":0.0097},{"kraken":"LTCUSD","return":0.0151},{"kraken":"XXBTZUSD","return":0.0194},{"kraken":"ETHUSD","return":0.0198},{"kraken":"XRPUSD","return":0.0201}]},{"principal":300000,"data":[{"kraken":"UNIUSD","return":0.0053},{"kraken":"ADAUSD","return":0.0101},{"kraken":"LTCUSD","return":0.0155},{"kraken":"XXBTZUSD","return":0.02},{"kraken":"ETHUSD","return":0.0203},{"kraken":"XRPUSD","return":0.0205}]},{"principal":400000,"data":[{"kraken":"UNIUSD","return":0.0055},{"kraken":"ADAUSD","return":0.0104},{"kraken":"LTCUSD","return":0.0158},{"kraken":"XXBTZUSD","return":0.0203},{"kraken":"ETHUSD","return":0.0205},{"kraken":"XRPUSD","return":0.0208}]},{"principal":500000,"data":[{"kraken":"UNIUSD","return":0.0057},{"kraken":"ADAUSD","return":0.0105},{"kraken":"LTCUSD","return":0.0159},{"kraken":"XXBTZUSD","return":0.0205},{"kraken":"ETHUSD","return":0.0207},{"kraken":"XRPUSD","return":0.0209}]},{"principal":600000,"data":[{"kraken":"UNIUSD","return":0.0058},{"kraken":"ADAUSD","return":0.0106},{"kraken":"LTCUSD","return":0.016},{"kraken":"XXBTZUSD","return":0.0207},{"kraken":"ETHUSD","return":0.0208},{"kraken":"XRPUSD","return":0.021}]},{"principal":700000,"data":[{"kraken":"UNIUSD","return":0.0058},{"kraken":"ADAUSD","return":0.0107},{"kraken":"LTCUSD","return":0.0161},{"kraken":"XXBTZUSD","return":0.0207},{"kraken":"ETHUSD","return":0.0208},{"kraken":"XRPUSD","return":0.0211}]},{"principal":800000,"data":[{"kraken":"UNIUSD","return":0.0059},{"kraken":"ADAUSD","return":0.0107},{"kraken":"LTCUSD","return":0.0161},{"kraken":"XXBTZUSD","return":0.0208},{"kraken":"ETHUSD","return":0.0209},{"kraken":"XRPUSD","return":0.0212}]},{"principal":900000,"data":[{"kraken":"UNIUSD","return":0.0059},{"kraken":"ADAUSD","return":0.0108},{"kraken":"LTCUSD","return":0.0162},{"kraken":"XXBTZUSD","return":0.0209},{"kraken":"ETHUSD","return":0.0209},{"kraken":"XRPUSD","return":0.0212}]},{"principal":1000000,"data":[{"kraken":"UNIUSD","return":0.0059},{"kraken":"ADAUSD","return":0.0108},{"kraken":"LTCUSD","return":0.0162},{"kraken":"XXBTZUSD","return":0.0209},{"kraken":"ETHUSD","return":0.021},{"kraken":"XRPUSD","return":0.0212}]}]
