[{"principal":100000,"data":[{"kraken":"UNIUSD","return":-0.0064},{"kraken":"ADAUSD","return":-0.0059},{"kraken":"ETHUSD","return":0.0185},{"kraken":"XXBTZUSD","return":0.0191},{"kraken":"XRPUSD","return":0.0194},{"kraken":"LTCUSD","return":0.0198}]},{"principal":200000,"data":[{"kraken":"UNIUSD","return":-0.0058},{"kraken":"ADAUSD","return":-0.0056},{"kraken":"ETHUSD","return":0.0193},{"kraken":"XRPUSD","return":0.0197},{"kraken":"XXBTZUSD","return":0.0199},{"kraken":"LTCUSD","return":0.0201}]},{"principal":300000,"data":[{"kraken":"UNIUSD","return":-0.0055},{"kraken":"ADAUSD","return":-0.0055},{"kraken":"ETHUSD","return":0.0195},{"kraken":"XRPUSD","return":0.0198},{"kraken":"XXBTZUSD","return":0.0201},{"kraken":"LTCUSD","return":0.0202}]},{"principal":400000,"data":[{"kraken":"ADAUSD","return":-0.0055},{"kraken":"UNIUSD","return":-0.0054},{"kraken":"ETHUSD","return":0.0197},{"kraken":"XRPUSD","return":0.0199},{"kraken":"XXBTZUSD","return":0.0203},{"kraken":"LTCUSD","return":0.0203}]},{"principal":500000,"data":[{"kraken":"ADAUSD","return":-0.0054},{"kraken":"UNIUSD","return":-0.0054},{"kraken":"ETHUSD","return":0.0197},{"kraken":"XRPUSD","return":0.0199},{"kraken":"LTCUSD","return":0.0203},{"kraken":"XXBTZUSD","return":0.0203}]},{"principal":600000,"data":[{"kraken":"ADAUSD","return":-0.0054},{"kraken":"UNIUSD","return":-0.0053},{"kraken":"ETHUSD","return":0.0198},{"kraken":"XRPUSD","return":0.0199},{"kraken":"LTCUSD","return":0.0203},{"kraken":"XXBTZUSD","return":0.0204}]},{"principal":700000,"data":[{"kraken":"ADAUSD","return":-0.0054},{"kraken":"UNIUSD","return":-0.0053},{"kraken":"ETHUSD","return":0.0198},{"kraken":"XRPUSD","return":0.0199},{"kraken":"LTCUSD","return":0.0203},{"kraken":"XXBTZUSD","return":0.0204}]},{"principal":800000,"data":[{"kraken":"ADAUSD","return":-0.0054},{"kraken":"UNIUSD","return":-0.0053},{"kraken":"ETHUSD","return":0.0199},{"kraken":"XRPUSD","return":0.0199},{"kraken":"LTCUSD","return":0.0204},{"kraken":"XXBTZUSD","return":0.0205}]},{"principal":900000,"data":[{"kraken":"ADAUSD","return":-0.0054},{"kraken":"UNIUSD","return":-0.0053},{"kraken":"ETHUSD","return":0.0199},{"kraken":"XRPUSD","return":0.0199},{"kraken":"LTCUSD","return":0.0204},{"kraken":"XXBTZUSD","return":0.0205}]},{"principal":1000000,"data":[{"kraken":"ADAUSD","return":-0.0054},{"kraken":"UNIUSD","return":-0.0052},{"kraken":"ETHUSD","return":0.0199},{"kraken":"XRPUSD","return":0.0199},{"kraken":"LTCUSD","return":0.0204},{"kraken":"XXBTZUSD","return":0.0205}]}]
