[{"principal":100000,"data":[{"kraken":"UNIUSD","return":-0.015},{"kraken":"ADAUSD","return":0.0061},{"kraken":"XXBTZUSD","return":0.0104},{"kraken":"XRPUSD","return":0.0107},{"kraken":"LTCUSD","return":0.0118},{"kraken":"ETHUSD","return":0.0131}]},{"principal":200000,"data":[{"kraken":"UNIUSD","return":-0.0136},{"kraken":"ADAUSD","return":0.0076},{"kraken":"XRPUSD","return":0.0122},{"kraken":"XXBTZUSD","return":0.0122},{"kraken":"LTCUSD","return":0.0133},{"kraken":"ETHUSD","return":0.0145}]},{"principal":300000,"data":[{"kraken":"UNIUSD","return":-0.0132},{"kraken":"ADAUSD","return":0.0081},{"kraken":"XRPUSD","return":0.0127},{"kraken":"XXBTZUSD","return":0.0128},{"kraken":"LTCUSD","return":0.0138},{"kraken":"ETHUSD","return":0.015}]},{"principal":400000,"data":[{"kraken":"UNIUSD","return":-0.0129},{"kraken":"ADAUSD","return":0.0083},{"kraken":"XRPUSD","return":0.0129},{"kraken":"XXBTZUSD","return":0.0131},{"kraken":"LTCUSD","return":0.014},{"kraken":"ETHUSD","return":0.0153}]},{"principal":500000,"data":[{"kraken":"UNIUSD","return":-0.0128},{"kraken":"ADAUSD","return":0.0084},{"kraken":"XRPUSD","return":0.0131},{"kraken":"XXBTZUSD","return":0.0133},{"kraken":"LTCUSD","return":0.0142},{"kraken":"ETHUSD","return":0.0154}]},{"principal":600000,"data":[{"kraken":"UNIUSD","return":-0.0127},{"kraken":"ADAUSD","return":0.0085},{"kraken":"XRPUSD","return":0.0132},{"kraken":"XXBTZUSD","return":0.0135},{"kraken":"LTCUSD","return":0.0143},{"kraken":"ETHUSD","return":0.0155}]},{"principal":700000,"data":[{"kraken":"UNIUSD","return":-0.0126},{"kraken":"ADAUSD","return":0.0086},{"kraken":"XRPUSD","return":0.0132},{"kraken":"XXBTZUSD","return":0.0135},{"kraken":"LTCUSD","return":0.0143},{"kraken":"ETHUSD","return":0.0156}]},{"principal":800000,"data":[{"kraken":"UNIUSD","return":-0.0126},{"kraken":"ADAUSD","return":0.0087},{"kraken":"XRPUSD","return":0.0133},{"kraken":"XXBTZUSD","return":0.0136},{"kraken":"LTCUSD","return":0.0144},{"kraken":"ETHUSD","return":0.0157}]},{"principal":900000,"data":[{"kraken":"UNIUSD","return":-0.0125},{"kraken":"ADAUSD","return":0.0087},{"kraken":"XRPUSD","return":0.0133},{"kraken":"XXBTZUSD","return":0.0137},{"kraken":"LTCUSD","return":0.0144},{"kraken":"ETHUSD","return":0.0157}]},{"principal":1000000,"data":[{"kraken":"UNIUSD","return":-0.0125},{"kraken":"ADAUSD","return":0.0087},{"kraken":"XRPUSD","return":0.0133},{"kraken":"XXBTZUSD","return":0.0137},{"kraken":"LTCUSD","return":0.0145},{"kraken":"ETHUSD","return":0.0157}]}]
