[{"principal":100000,"data":[{"kraken":"ADAUSD","return":0.0201},{"kraken":"LTCUSD","return":0.0202},{"kraken":"XXBTZUSD","return":0.0212},{"kraken":"ETHUSD","return":0.0214},{"kraken":"XRPUSD","return":0.0241},{"kraken":"UNIUSD","return":0.0283}]},{"principal":200000,"data":[{"kraken":"ADAUSD","return":0.0204},{"kraken":"LTCUSD","return":0.0205},{"kraken":"XXBTZUSD","return":0.0221},{"kraken":"ETHUSD","return":0.0222},{"kraken":"XRPUSD","return":0.0244},{"kraken":"UNIUSD","return":0.0289}]},{"principal":300000,"data":[{"kraken":"ADAUSD","return":0.0205},{"kraken":"LTCUSD","return":0.0206},{"kraken":"XXBTZUSD","return":0.0223},{"kraken":"ETHUSD","return":0.0224},{"kraken":"XRPUSD","return":0.0245},{"kraken":"UNIUSD","return":0.0291}]},{"principal":400000,"data":[{"kraken":"ADAUSD","return":0.0205},{"kraken":"LTCUSD","return":0.0206},{"kraken":"XXBTZUSD","return":0.0225},{"kraken":"ETHUSD","return":0.0226},{"kraken":"XRPUSD","return":0.0246},{"kraken":"UNIUSD","return":0.0292}]},{"principal":500000,"data":[{"kraken":"ADAUSD","return":0.0206},{"kraken":"LTCUSD","return":0.0207},{"kraken":"XXBTZUSD","return":0.0226},{"kraken":"ETHUSD","return":0.0226},{"kraken":"XRPUSD","return":0.0246},{"kraken":"UNIUSD","return":0.0293}]},{"principal":600000,"data":[{"kraken":"ADAUSD","return":0.0206},{"kraken":"LTCUSD","return":0.0207},{"kraken":"XXBTZUSD","return":0.0226},{"kraken":"ETHUSD","return":0.0227},{"kraken":"XRPUSD","return":0.0246},{"kraken":"UNIUSD","return":0.0293}]},{"principal":700000,"data":[{"kraken":"ADAUSD","return":0.0206},{"kraken":"LTCUSD","return":0.0207},{"kraken":"XXBTZUSD","return":0.0227},{"kraken":"ETHUSD","return":0.0227},{"kraken":"XRPUSD","return":0.0246},{"kraken":"UNIUSD","return":0.0294}]},{"principal":800000,"data":[{"kraken":"ADAUSD","return":0.0206},{"kraken":"LTCUSD","return":0.0207},{"kraken":"XXBTZUSD","return":0.0227},{"kraken":"ETHUSD","return":0.0227},{"kraken":"XRPUSD","return":0.0247},{"kraken":"UNIUSD","return":0.0294}]},{"principal":900000,"data":[{"kraken":"ADAUSD","return":0.0206},{"kraken":"LTCUSD","return":0.0207},{"kraken":"XXBTZUSD","return":0.0227},{"kraken":"ETHUSD","return":0.0228},{"kraken":"XRPUSD","return":0.0247},{"kraken":"UNIUSD","return":0.0294}]},{"principal":1000000,"data":[{"kraken":"ADAUSD","return":0.0206},{"kraken":"LTCUSD","return":0.0207},{"kraken":"XXBTZUSD","return":0.0227},{"kraken":"ETHUSD","return":0.0228},{"kraken":"XRPUSD","return":0.0247},{"kraken":"UNIUSD","return":0.0294}]}]
