[{"principal":100000,"data":[{"kraken":"LTCUSD","return":0.0003},{"kraken":"ADAUSD","return":0.0107},{"kraken":"XXBTZUSD","return":0.0114},{"kraken":"ETHUSD","return":0.0122},{"kraken":"XRPUSD","return":0.0137},{"kraken":"UNIUSD","return":0.0364}]},{"principal":200000,"data":[{"kraken":"LTCUSD","return":0.0006},{"kraken":"ADAUSD","return":0.011},{"kraken":"XXBTZUSD","return":0.0122},{"kraken":"ETHUSD","return":0.013},{"kraken":"XRPUSD","return":0.0141},{"kraken":"UNIUSD","return":0.0371}]},{"principal":300000,"data":[{"kraken":"LTCUSD","return":0.0007},{"kraken":"ADAUSD","return":0.0111},{"kraken":"XXBTZUSD","return":0.0125},{"kraken":"ETHUSD","return":0.0132},{"kraken":"XRPUSD","return":0.0142},{"kraken":"UNIUSD","return":0.0373}]},{"principal":400000,"data":[{"kraken":"LTCUSD","return":0.0008},{"kraken":"ADAUSD","return":0.0112},{"kraken":"XXBTZUSD","return":0.0126},{"kraken":"ETHUSD","return":0.0134},{"kraken":"XRPUSD","return":0.0142},{"kraken":"UNIUSD","return":0.0374}]},{"principal":500000,"data":[{"kraken":"LTCUSD","return":0.0008},{"kraken":"ADAUSD","return":0.0112},{"kraken":"XXBTZUSD","return":0.0127},{"kraken":"ETHUSD","return":0.0134},{"kraken":"XRPUSD","return":0.0142},{"kraken":"UNIUSD","return":0.0375}]},{"principal":600000,"data":[{"kraken":"LTCUSD","return":0.0008},{"kraken":"ADAUSD","return":0.0112},{"kraken":"XXBTZUSD","return":0.0128},{"kraken":"ETHUSD","return":0.0135},{"kraken":"XRPUSD","return":0.0143},{"kraken":"UNIUSD","return":0.0375}]},{"principal":700000,"data":[{"kraken":"LTCUSD","return":0.0009},{"kraken":"ADAUSD","return":0.0112},{"kraken":"XXBTZUSD","return":0.0128},{"kraken":"ETHUSD","return":0.0135},{"kraken":"XRPUSD","return":0.0143},{"kraken":"UNIUSD","return":0.0376}]},{"principal":800000,"data":[{"kraken":"LTCUSD","return":0.0009},{"kraken":"ADAUSD","return":0.0112},{"kraken":"XXBTZUSD","return":0.0128},{"kraken":"ETHUSD","return":0.0136},{"kraken":"XRPUSD","return":0.0143},{"kraken":"UNIUSD","return":0.0376}]},{"principal":900000,"data":[{"kraken":"LTCUSD","return":0.0009},{"kraken":"ADAUSD","return":0.0113},{"kraken":"XXBTZUSD","return":0.0129},{"kraken":"ETHUSD","return":0.0136},{"kraken":"XRPUSD","return":0.0143},{"kraken":"UNIUSD","return":0.0376}]},{"principal":1000000,"data":[{"kraken":"LTCUSD","return":0.0009},{"kraken":"ADAUSD","return":0.0113},{"kraken":"XXBTZUSD","return":0.0129},{"kraken":"ETHUSD","return":0.0136},{"kraken":"XRPUSD","return":0.0143},{"kraken":"UNIUSD","return":0.0376}]}]
