[{"principal":100000,"data":[{"kraken":"UNIUSD","return":-0.0051},{"kraken":"ADAUSD","return":-0.001},{"kraken":"LTCUSD","return":0.0002},{"kraken":"ETHUSD","return":0.0084},{"kraken":"XXBTZUSD","return":0.01},{"kraken":"XRPUSD","return":0.0105}]},{"principal":200000,"data":[{"kraken":"UNIUSD","return":-0.0044},{"kraken":"ADAUSD","return":-0.0007},{"kraken":"LTCUSD","return":0.0005},{"kraken":"ETHUSD","return":0.0092},{"kraken":"XRPUSD","return":0.0108},{"kraken":"XXBTZUSD","return":0.0108}]},{"principal":300000,"data":[{"kraken":"UNIUSD","return":-0.0042},{"kraken":"ADAUSD","return":-0.0006},{"kraken":"LTCUSD","return":0.0006},{"kraken":"ETHUSD","return":0.0094},{"kraken":"XRPUSD","return":0.0109},{"kraken":"XXBTZUSD","return":0.011}]},{"principal":400000,"data":[{"kraken":"UNIUSD","return":-0.0041},{"kraken":"ADAUSD","return":-0.0005},{"kraken":"LTCUSD","return":0.0007},{"kraken":"ETHUSD","return":0.0095},{"kraken":"XRPUSD","return":0.0109},{"kraken":"XXBTZUSD","return":0.0112}]},{"principal":500000,"data":[{"kraken":"UNIUSD","return":-0.004},{"kraken":"ADAUSD","return":-0.0005},{"kraken":"LTCUSD","return":0.0007},{"kraken":"ETHUSD","return":0.0096},{"kraken":"XRPUSD","return":0.0109},{"kraken":"XXBTZUSD","return":0.0112}]},{"principal":600000,"data":[{"kraken":"UNIUSD","return":-0.004},{"kraken":"ADAUSD","return":-0.0005},{"kraken":"LTCUSD","return":0.0007},{"kraken":"ETHUSD","return":0.0097},{"kraken":"XRPUSD","return":0.011},{"kraken":"XXBTZUSD","return":0.0113}]},{"principal":700000,"data":[{"kraken":"UNIUSD","return":-0.004},{"kraken":"ADAUSD","return":-0.0005},{"kraken":"LTCUSD","return":0.0007},{"kraken":"ETHUSD","return":0.0097},{"kraken":"XRPUSD","return":0.011},{"kraken":"XXBTZUSD","return":0.0113}]},{"principal":800000,"data":[{"kraken":"UNIUSD","return":-0.0039},{"kraken":"ADAUSD","return":-0.0004},{"kraken":"LTCUSD","return":0.0007},{"kraken":"ETHUSD","return":0.0097},{"kraken":"XRPUSD","return":0.011},{"kraken":"XXBTZUSD","return":0.0114}]},{"principal":900000,"data":[{"kraken":"UNIUSD","return":-0.0039},{"kraken":"ADAUSD","return":-0.0004},{"kraken":"LTCUSD","return":0.0007},{"kraken":"ETHUSD","return":0.0097},{"kraken":"XRPUSD","return":0.011},{"kraken":"XXBTZUSD","return":0.0114}]},{"principal":1000000,"data":[{"kraken":"UNIUSD","return":-0.0039},{"kraken":"ADAUSD","return":-0.0004},{"kraken":"LTCUSD","return":0.0007},{"kraken":"ETHUSD","return":0.0098},{"kraken":"XRPUSD","return":0.011},{"kraken":"XXBTZUSD","return":0.0114}]}]
