[{"principal":100000,"data":[{"kraken":"LTCUSD","return":0.0066},{"kraken":"ADAUSD","return":0.0087},{"kraken":"ETHUSD","return":0.0133},{"kraken":"XRPUSD","return":0.0144},{"kraken":"XXBTZUSD","return":0.0145},{"kraken":"UNIUSD","return":0.0288}]},{"principal":200000,"data":[{"kraken":"LTCUSD","return":0.0069},{"kraken":"ADAUSD","return":0.009},{"kraken":"ETHUSD","return":0.014},{"kraken":"XRPUSD","return":0.0147},{"kraken":"XXBTZUSD","return":0.0153},{"kraken":"UNIUSD","return":0.0295}]},{"principal":300000,"data":[{"kraken":"LTCUSD","return":0.007},{"kraken":"ADAUSD","return":0.0091},{"kraken":"ETHUSD","return":0.0143},{"kraken":"XRPUSD","return":0.0148},{"kraken":"XXBTZUSD","return":0.0155},{"kraken":"UNIUSD","return":0.0297}]},{"principal":400000,"data":[{"kraken":"LTCUSD","return":0.007},{"kraken":"ADAUSD","return":0.0092},{"kraken":"ETHUSD","return":0.0144},{"kraken":"XRPUSD","return":0.0149},{"kraken":"XXBTZUSD","return":0.0157},{"kraken":"UNIUSD","return":0.0299}]},{"principal":500000,"data":[{"kraken":"LTCUSD","return":0.007},{"kraken":"ADAUSD","return":0.0092},{"kraken":"ETHUSD","return":0.0145},{"kraken":"XRPUSD","return":0.0149},{"kraken":"XXBTZUSD","return":0.0158},{"kraken":"UNIUSD","return":0.0299}]},{"principal":600000,"data":[{"kraken":"LTCUSD","return":0.0071},{"kraken":"ADAUSD","return":0.0092},{"kraken":"ETHUSD","return":0.0145},{"kraken":"XRPUSD","return":0.0149},{"kraken":"XXBTZUSD","return":0.0158},{"kraken":"UNIUSD","return":0.03}]},{"principal":700000,"data":[{"kraken":"LTCUSD","return":0.0071},{"kraken":"ADAUSD","return":0.0092},{"kraken":"ETHUSD","return":0.0146},{"kraken":"XRPUSD","return":0.0149},{"kraken":"XXBTZUSD","return":0.0158},{"kraken":"UNIUSD","return":0.03}]},{"principal":800000,"data":[{"kraken":"LTCUSD","return":0.0071},{"kraken":"ADAUSD","return":0.0092},{"kraken":"ETHUSD","return":0.0146},{"kraken":"XRPUSD","return":0.015},{"kraken":"XXBTZUSD","return":0.0159},{"kraken":"UNIUSD","return":0.03}]},{"principal":900000,"data":[{"kraken":"LTCUSD","return":0.0071},{"kraken":"ADAUSD","return":0.0093},{"kraken":"ETHUSD","return":0.0146},{"kraken":"XRPUSD","return":0.015},{"kraken":"XXBTZUSD","return":0.0159},{"kraken":"UNIUSD","return":0.03}]},{"principal":1000000,"data":[{"kraken":"LTCUSD","return":0.0071},{"kraken":"ADAUSD","return":0.0093},{"kraken":"ETHUSD","return":0.0146},{"kraken":"XRPUSD","return":0.015},{"kraken":"XXBTZUSD","return":0.0159},{"kraken":"UNIUSD","return":0.0301}]}]
