[{"principal":100000,"data":[{"kraken":"LTCUSD","return":0.0025},{"kraken":"ADAUSD","return":0.0043},{"kraken":"XRPUSD","return":0.0098},{"kraken":"XXBTZUSD","return":0.0108},{"kraken":"ETHUSD","return":0.0113},{"kraken":"UNIUSD","return":0.0214}]},{"principal":200000,"data":[{"kraken":"LTCUSD","return":0.0028},{"kraken":"ADAUSD","return":0.0047},{"kraken":"XRPUSD","return":0.0101},{"kraken":"XXBTZUSD","return":0.0117},{"kraken":"ETHUSD","return":0.0121},{"kraken":"UNIUSD","return":0.0222}]},{"principal":300000,"data":[{"kraken":"LTCUSD","return":0.0029},{"kraken":"ADAUSD","return":0.0048},{"kraken":"XRPUSD","return":0.0102},{"kraken":"XXBTZUSD","return":0.012},{"kraken":"ETHUSD","return":0.0124},{"kraken":"UNIUSD","return":0.0225}]},{"principal":400000,"data":[{"kraken":"LTCUSD","return":0.0029},{"kraken":"ADAUSD","return":0.0048},{"kraken":"XRPUSD","return":0.0103},{"kraken":"XXBTZUSD","return":0.0121},{"kraken":"ETHUSD","return":0.0125},{"kraken":"UNIUSD","return":0.0226}]},{"principal":500000,"data":[{"kraken":"LTCUSD","return":0.003},{"kraken":"ADAUSD","return":0.0048},{"kraken":"XRPUSD","return":0.0103},{"kraken":"XXBTZUSD","return":0.0122},{"kraken":"ETHUSD","return":0.0126},{"kraken":"UNIUSD","return":0.0227}]},{"principal":600000,"data":[{"kraken":"LTCUSD","return":0.003},{"kraken":"ADAUSD","return":0.0049},{"kraken":"XRPUSD","return":0.0103},{"kraken":"XXBTZUSD","return":0.0123},{"kraken":"ETHUSD","return":0.0127},{"kraken":"UNIUSD","return":0.0227}]},{"principal":700000,"data":[{"kraken":"LTCUSD","return":0.003},{"kraken":"ADAUSD","return":0.0049},{"kraken":"XRPUSD","return":0.0104},{"kraken":"XXBTZUSD","return":0.0123},{"kraken":"ETHUSD","return":0.0127},{"kraken":"UNIUSD","return":0.0227}]},{"principal":800000,"data":[{"kraken":"LTCUSD","return":0.003},{"kraken":"ADAUSD","return":0.0049},{"kraken":"XRPUSD","return":0.0104},{"kraken":"XXBTZUSD","return":0.0123},{"kraken":"ETHUSD","return":0.0127},{"kraken":"UNIUSD","return":0.0228}]},{"principal":900000,"data":[{"kraken":"LTCUSD","return":0.003},{"kraken":"ADAUSD","return":0.0049},{"kraken":"XRPUSD","return":0.0104},{"kraken":"XXBTZUSD","return":0.0124},{"kraken":"ETHUSD","return":0.0128},{"kraken":"UNIUSD","return":0.0228}]},{"principal":1000000,"data":[{"kraken":"LTCUSD","return":0.003},{"kraken":"ADAUSD","return":0.0049},{"kraken":"XRPUSD","return":0.0104},{"kraken":"XXBTZUSD","return":0.0124},{"kraken":"ETHUSD","return":0.0128},{"kraken":"UNIUSD","return":0.0228}]}]
