[{"principal":100000,"data":[{"kraken":"XXBTZUSD","return":0.0136}]},{"principal":200000,"data":[{"kraken":"XXBTZUSD","return":0.0155}]},{"principal":300000,"data":[{"kraken":"XXBTZUSD","return":0.0161}]},{"principal":400000,"data":[{"kraken":"XXBTZUSD","return":0.0164}]},{"principal":500000,"data":[{"kraken":"XXBTZUSD","return":0.0166}]},{"principal":600000,"data":[{"kraken":"XXBTZUSD","return":0.0167}]},{"principal":700000,"data":[{"kraken":"XXBTZUSD","return":0.0168}]},{"principal":800000,"data":[{"kraken":"XXBTZUSD","return":0.0169}]},{"principal":900000,"data":[{"kraken":"XXBTZUSD","return":0.017}]},{"principal":1000000,"data":[{"kraken":"XXBTZUSD","return":0.017}]}]
