[{"principal":200000,"data":[{"kraken":"XXBTZUSD","return":0.0064}]},{"principal":300000,"data":[{"kraken":"XXBTZUSD","return":0.0067}]},{"principal":400000,"data":[{"kraken":"XXBTZUSD","return":0.0069}]},{"principal":500000,"data":[{"kraken":"XXBTZUSD","return":0.007}]},{"principal":600000,"data":[{"kraken":"XXBTZUSD","return":0.0071}]},{"principal":700000,"data":[{"kraken":"XXBTZUSD","return":0.0071}]},{"principal":800000,"data":[{"kraken":"XXBTZUSD","return":0.0071}]},{"principal":900000,"data":[{"kraken":"XXBTZUSD","return":0.0072}]},{"principal":1000000,"data":[{"kraken":"XXBTZUSD","return":0.0072}]},{"principal":100000,"data":[{"kraken":"XRPUSD","return":0.0059}]}]
